rearrangement_algorithm/__init__.py
rearrangement_algorithm/base.py
rearrangement_algorithm-0.1.1.dist-info/LICENSE
rearrangement_algorithm-0.1.1.dist-info/METADATA
rearrangement_algorithm-0.1.1.dist-info/WHEEL
rearrangement_algorithm-0.1.1.dist-info/top_level.txt
rearrangement_algorithm-0.1.1.dist-info/RECORD
