Metadata-Version: 2.1
Name: rearrangement-algorithm
Version: 0.1.1
Summary: Implementation of the rearrangement algorithm
Home-page: https://gitlab.com/klb2/rearrangement-algorithm
Author: Karl Besser
Author-email: k.besser@tu-bs.de
License: GPLv3
Project-URL: Documentation, https://rearrangement-algorithm.readthedocs.io
Project-URL: Source Code, https://gitlab.com/klb2/rearrangement-algorithm
Keywords: rearrangement algorith,quantitative risk management
Platform: UNKNOWN
License-File: LICENSE
Requires-Dist: numpy
Requires-Dist: scipy
